spotify_to_ytmusic/__init__.py
spotify_to_ytmusic/controllers.py
spotify_to_ytmusic/main.py
spotify_to_ytmusic/settings.ini.example
spotify_to_ytmusic/settings.py
spotify_to_ytmusic/setup.py
spotify_to_ytmusic/spotify.py
spotify_to_ytmusic/ytmusic.py
spotify_to_ytmusic/utils/__init__.py
spotify_to_ytmusic/utils/browser.py
spotify_to_ytmusic/utils/cache_manager.py
spotify_to_ytmusic/utils/match.py
spotify_to_ytmusic-0.8.0.dist-info/licenses/LICENSE
spotify_to_ytmusic-0.8.0.dist-info/METADATA
spotify_to_ytmusic-0.8.0.dist-info/WHEEL
spotify_to_ytmusic-0.8.0.dist-info/entry_points.txt
spotify_to_ytmusic-0.8.0.dist-info/top_level.txt
spotify_to_ytmusic-0.8.0.dist-info/RECORD
