Metadata-Version: 2.4
Name: spotify_to_ytmusic
Version: 0.8.0
Summary: Transfer Spotify playlists to YouTube Music
Author-email: sigma67 <sigma67.github@gmail.com>
License: MIT License
Project-URL: homepage, https://github.com/sigma67/spotify_to_ytmusic
Project-URL: repository, https://github.com/sigma67/spotify_to_ytmusic
Classifier: Programming Language :: Python :: 3
Classifier: Programming Language :: Python :: 3.10
Classifier: Programming Language :: Python :: 3.11
Classifier: Programming Language :: Python :: 3.12
Classifier: Programming Language :: Python :: 3.13
Classifier: License :: OSI Approved :: MIT License
Requires-Python: >=3.10
License-File: LICENSE
Requires-Dist: ytmusicapi>=1.11.0rc1
Requires-Dist: spotipy>=2.25.0
Requires-Dist: platformdirs>=3.2
Dynamic: license-file
